{
  "schema_version": "2.0",
  "canon_name": "Basileian Canon (Jesus Tradition)",
  "canon_version": "v3",
  "description": "Original-language source texts for the Basileian / Jesus Tradition canon. The canon comprises Koine Greek New Testament and apostolic-fathers material plus Sahidic Coptic from Nag Hammadi. Greek material is presented in canon-style unaccented form preserving uncial-manuscript convention through approximately the 9th century.",
  "languages": {
    "grc": {
      "name": "Koine Greek",
      "script": "Greek",
      "convention": "unaccented (no breathings, no accents, no iota subscripts); final sigma rendered as σ; medial mu rendered as µ"
    },
    "cop": {
      "name": "Sahidic Coptic",
      "script": "Coptic",
      "convention": "standard scholarly transcription preserving supralinear strokes and nomina sacra"
    }
  },
  "verse_id_format": "{book}.{chapter_or_logion}.{verse}",
  "verse_id_examples": [
    "mark.1.3",
    "thomas.113.1",
    "1cor.15.3",
    "acts.9.1",
    "luke.23.34a",
    "didache.9.4"
  ],
  "verse_id_book_codes": {
    "matthew": "Gospel of Matthew",
    "mark": "Gospel of Mark",
    "luke": "Gospel of Luke",
    "john": "Gospel of John",
    "acts": "Acts of the Apostles",
    "1cor": "1 Corinthians",
    "galatians": "Galatians",
    "thomas": "Gospel of Thomas (logion-keyed)",
    "didache": "Didache"
  },
  "sections": [
    {"id": "tier1_a_mark", "tier": 1, "letter": "A", "title": "The Gospel of Mark", "language": "grc", "filename": "tier1_a_mark.json", "completeness": "complete"},
    {"id": "tier1_b_q", "tier": 1, "letter": "B", "title": "Q — The Sayings Source", "language": "grc", "filename": "tier1_b_q.json", "completeness": "complete", "structure_note": "Q is reconstructed; each pericope provides Lukan and Matthean parallels (where extant) under lk_versions and mt_versions arrays rather than a single verses array."},
    {"id": "tier1_c_special_l", "tier": 1, "letter": "C", "title": "Special L — Lukan Material with Strong Coherence", "language": "grc", "filename": "tier1_c_special_l.json", "completeness": "complete"},
    {"id": "tier1_d_special_m", "tier": 1, "letter": "D", "title": "Special M — Matthean Material with Strong Coherence", "language": "grc", "filename": "tier1_d_special_m.json", "completeness": "complete"},
    {"id": "tier1_e_thomas", "tier": 1, "letter": "E", "title": "The Gospel of Thomas — Selected Sayings", "language": "cop", "filename": "tier1_e_thomas.json", "completeness": "partial", "completeness_note": "16 of 57 logia have Coptic text; 41 are pending source-fetch from public-domain Nag Hammadi editions."},
    {"id": "tier1_f_john", "tier": 1, "letter": "F", "title": "The Gospel of John — Selected Pericopes", "language": "grc", "filename": "tier1_f_john.json", "completeness": "partial", "completeness_note": "11 of 12 pericopes complete; Pericope Adulterae (7:53–8:11) pending fetch from Byzantine textform."},
    {"id": "tier2_a_last_supper", "tier": 2, "letter": "A", "title": "The Last Supper Words (1 Cor 11:23–26)", "language": "grc", "filename": "tier2_a_last_supper.json", "completeness": "complete"},
    {"id": "tier2_b_appearances", "tier": 2, "letter": "B", "title": "The Resurrection Appearances List (1 Cor 15:3b–7)", "language": "grc", "filename": "tier2_b_appearances.json", "completeness": "complete"},
    {"id": "tier2_c_pauline_claims", "tier": 2, "letter": "C", "title": "Pauline First-Person Appearance Claims and Damascus Accounts", "language": "grc", "filename": "tier2_c_pauline_claims.json", "completeness": "complete"},
    {"id": "tier2_d_ascension", "tier": 2, "letter": "D", "title": "Ascension Narratives (Acts 1:1–11; Luke 24:50–53)", "language": "grc", "filename": "tier2_d_ascension.json", "completeness": "complete"},
    {"id": "tier2_e_agraphon", "tier": 2, "letter": "E", "title": "Agraphon (Acts 20:35)", "language": "grc", "filename": "tier2_e_agraphon.json", "completeness": "complete"},
    {"id": "tier2_f_didache", "tier": 2, "letter": "F", "title": "The Didache 8:2 and 9–10", "language": "grc", "filename": "tier2_f_didache.json", "completeness": "complete"},
    {"id": "tier3_a_egerton", "tier": 3, "letter": "A", "title": "Papyrus Egerton 2", "language": "grc", "filename": "tier3_a_egerton.json", "completeness": "placeholder", "completeness_note": "Greek text pending fetch from Bell & Skeat 1935 or Kraus, Nicklas & Kruger 2009."},
    {"id": "tier3_b_poxy_1224", "tier": 3, "letter": "B", "title": "Papyrus Oxyrhynchus 1224", "language": "grc", "filename": "tier3_b_poxy_1224.json", "completeness": "placeholder", "completeness_note": "Greek text pending fetch from Grenfell & Hunt 1914."},
    {"id": "tier3_c_poxy_840", "tier": 3, "letter": "C", "title": "Papyrus Oxyrhynchus 840", "language": "grc", "filename": "tier3_c_poxy_840.json", "completeness": "placeholder", "completeness_note": "Greek text pending fetch from Grenfell & Hunt 1908."},
    {"id": "tier3_d_poxy_5575", "tier": 3, "letter": "D", "title": "Papyrus Oxyrhynchus 5575", "language": "grc", "filename": "tier3_d_poxy_5575.json", "completeness": "external_only", "completeness_note": "Source text is copyrighted (EES 2023). Cannot be reproduced; placeholder includes citation and external URL."},
    {"id": "tier3_e_gospel_of_peter", "tier": 3, "letter": "E", "title": "The Gospel of Peter — Passion Material", "language": "grc", "filename": "tier3_e_gospel_of_peter.json", "completeness": "placeholder", "completeness_note": "Greek text pending fetch from Bouriant 1892 or Foster 2010."},
    {"id": "tier3_f_jewish_christian", "tier": 3, "letter": "F", "title": "Selected Citations from the Jewish-Christian Gospels", "language": "grc", "filename": "tier3_f_jewish_christian.json", "completeness": "placeholder", "completeness_note": "Greek/Latin text pending fetch from Origen, Jerome, Epiphanius primary sources or Klijn 1992."}
  ],
  "external_resources_recommendations": {
    "purpose": "The verse_id structure in this corpus (e.g., 'mark.1.3') is designed to join with public-domain biblical resources keyed to the same canonical reference format. The app can ingest any of the resources below as separate JSON files and join on verse_id to provide parallel-translation comparison, lexical lookup, and commentary view.",
    "parallel_translations_public_domain": [
      {"id": "kjv", "name": "King James Version (1769 Cambridge edition)", "year": 1611, "license": "public domain", "translation_philosophy": "formal equivalence; Elizabethan English"},
      {"id": "asv", "name": "American Standard Version", "year": 1901, "license": "public domain", "translation_philosophy": "formal equivalence; modernized KJV"},
      {"id": "ylt", "name": "Young's Literal Translation", "year": 1898, "license": "public domain", "translation_philosophy": "extremely literal; Hebrew-syntax-preserving"},
      {"id": "darby", "name": "Darby Translation", "year": 1890, "license": "public domain", "translation_philosophy": "literal; conservative-evangelical"},
      {"id": "web", "name": "World English Bible", "year": 2000, "license": "public domain", "translation_philosophy": "modern English ASV revision"}
    ],
    "lexicons_public_domain": [
      {"id": "strongs", "name": "Strong's Concordance and Lexicon", "year": 1890, "applies_to": "grc, hbo", "license": "public domain", "lookup_key": "Strong's number (e.g., G2098)"},
      {"id": "thayer", "name": "Thayer's Greek-English Lexicon of the New Testament", "year": 1889, "applies_to": "grc", "license": "public domain", "lookup_key": "Greek lemma"},
      {"id": "lsj", "name": "Liddell-Scott-Jones Greek-English Lexicon (Perseus public domain edition)", "year": 1940, "applies_to": "grc", "license": "public domain via Perseus", "lookup_key": "Greek lemma"},
      {"id": "crum", "name": "Crum's Coptic Dictionary", "year": 1939, "applies_to": "cop", "license": "public domain", "lookup_key": "Coptic lemma"}
    ],
    "commentaries_public_domain": [
      {"id": "jfb", "name": "Jamieson-Fausset-Brown Commentary", "year": 1871, "license": "public domain"},
      {"id": "matthew_henry", "name": "Matthew Henry's Commentary on the Whole Bible", "year": 1714, "license": "public domain"},
      {"id": "barnes", "name": "Barnes' Notes on the Bible", "year": 1834, "license": "public domain"},
      {"id": "clarke", "name": "Adam Clarke's Commentary on the Bible", "year": 1831, "license": "public domain"},
      {"id": "gill", "name": "John Gill's Exposition of the Whole Bible", "year": 1748, "license": "public domain"}
    ],
    "data_sources_for_app_developer": [
      {"name": "STEP Bible", "url": "https://stepbible.org/", "note": "Open-data biblical resources including parallel translations and lexicons; permissively licensed."},
      {"name": "Open Scriptures", "url": "https://github.com/openscriptures", "note": "Machine-readable biblical resources including Strong's lexicons, public-domain translations, morphologically-tagged Greek and Hebrew texts."},
      {"name": "MorphGNT", "url": "https://github.com/morphgnt/sblgnt", "note": "Morphologically-tagged SBLGNT (CC-BY-SA tagging on SBLGNT text). Useful for adding token-level lemma + Strong's data in a future revision of this corpus."},
      {"name": "Coptic SCRIPTORIUM", "url": "https://copticscriptorium.org/", "note": "Lemmatized and morphologically tagged Coptic corpora including Nag Hammadi (CC-BY licensed)."}
    ]
  },
  "future_revisions": {
    "description": "This corpus is intentionally minimal — text + transliteration + verse_id, no token-level data. Subsequent revisions can layer additional data without changing the existing structure.",
    "planned_layers": [
      {"layer": "token_data", "description": "Per-word lemma, Strong's number, morphological tag. Source: MorphGNT for Greek, Coptic SCRIPTORIUM for Coptic. Does not require schema changes — adds 'tokens' array per verse alongside existing 'text' field."},
      {"layer": "complete_apocrypha", "description": "Fetch and integrate the Greek text of P.Egerton 2, P.Oxy 1224, P.Oxy 840, Gospel of Peter, and Jewish-Christian gospel citations from public-domain primary editions."},
      {"layer": "complete_thomas", "description": "Fetch the remaining 41 Coptic logia from public-domain Nag Hammadi editions to complete the Thomas section."},
      {"layer": "pericope_adulterae", "description": "Fetch Greek text of John 7:53–8:11 from a Byzantine-textform source (Stephanus 1550 or Robinson-Pierpont)."},
      {"layer": "wh_reconciliation", "description": "Reconcile John, Tier 2 NT material, and any other SBLGNT-sourced sections to the WH 1881 text directly, replacing minor SBLGNT divergences."}
    ]
  }
}
